{
  "swagger": "2.0",
  "info": {
    "version": "1.0.0",
    "title": "Cookbook API",
    "description": "Documentation automatically generated by the <b>swagger-autogen</b> module."
  },
  "host": "localhost:3000",
  "basePath": "/",
  "tags": [
    {
      "name": "Auth",
      "description": "Authentications"
    }
  ],
  "schemes": [
    "http",
    "https"
  ],
  "securityDefinitions": {
    "apiKeyAuth": {
      "type": "apiKey",
      "in": "header",
      "name": "X-API-KEY",
      "description": "any description..."
    }
  },
  "consumes": [
    "application/json"
  ],
  "produces": [
    "application/json"
  ],
  "paths": {
    "/v1/auth/logout/{token}": {
      "delete": {
        "tags": [
          "Auth"
        ],
        "description": "Delete user session",
        "parameters": [
          {
            "name": "token",
            "in": "path",
            "required": true,
            "type": "string"
          }
        ],
        "responses": {
          "200": {
            "description": "OK"
          }
        }
      }
    },
    "/v1/auth/register": {
      "post": {
        "tags": [
          "Auth"
        ],
        "description": "Create a new user",
        "parameters": [
          {
            "name": "body",
            "in": "body",
            "schema": {
              "type": "object",
              "properties": {
                "username": {
                  "example": "any"
                },
                "password": {
                  "example": "any"
                },
                "repeatPassword": {
                  "example": "any"
                }
              }
            }
          }
        ],
        "responses": {
          "200": {
            "description": "OK"
          }
        }
      }
    },
    "/v1/auth/login": {
      "post": {
        "tags": [
          "Auth"
        ],
        "description": "Create new session",
        "parameters": [
          {
            "name": "body",
            "in": "body",
            "schema": {
              "type": "object",
              "properties": {
                "username": {
                  "example": "any"
                },
                "password": {
                  "example": "any"
                }
              }
            }
          }
        ],
        "responses": {
          "200": {
            "description": "OK"
          }
        }
      }
    }
  }
}